easy_pybind/__init__.py
easy_pybind/file_contents.py
easy_pybind/main.py
easy_pybind-1.0.0.dist-info/LICENSE
easy_pybind-1.0.0.dist-info/METADATA
easy_pybind-1.0.0.dist-info/WHEEL
easy_pybind-1.0.0.dist-info/entry_points.txt
easy_pybind-1.0.0.dist-info/top_level.txt
easy_pybind-1.0.0.dist-info/RECORD
